src/__init__.py
src/delta_lake/__init__.py
src/delta_lake/constants.py
src/delta_lake/delta_lake_python.py
src/delta_lake/delta_lake_spark.py
src/delta_lake/spark_session.py
src/utils/__init__.py
src/utils/cores.py
src/utils/logger.py
src/utils/trace_logger.py
python_prakashravip1-1.0.4.dist-info/LICENSE
python_prakashravip1-1.0.4.dist-info/WHEEL
python_prakashravip1-1.0.4.dist-info/METADATA
python_prakashravip1-1.0.4.dist-info/RECORD
