Metadata-Version: 2.1
Name: python-prakashravip1
Version: 1.0.4
Summary: Common Python Utility and Client Tools
Home-page: https://github.com/ravip18596/ravi-python-clients
License: Apache-2.0
Author: ravipnsit
Author-email: prakashravip1@gmail.com
Requires-Python: >=3.8,<4.0
Classifier: License :: OSI Approved :: Apache Software License
Classifier: Programming Language :: Python :: 3
Classifier: Programming Language :: Python :: 3.10
Classifier: Programming Language :: Python :: 3.8
Classifier: Programming Language :: Python :: 3.9
Requires-Dist: delta-spark (==1.2.1)
Project-URL: Repository, https://github.com/ravip18596/ravi-python-clients
